datastew/__init__.py
datastew/_version.py
datastew/embedding.py
datastew/exceptions.py
datastew/process/__init__.py
datastew/process/jsonl_adapter.py
datastew/process/mapping.py
datastew/process/ols.py
datastew/process/parsing.py
datastew/repository/__init__.py
datastew/repository/base.py
datastew/repository/model.py
datastew/repository/pagination.py
datastew/repository/postgresql.py
datastew/repository/sqllite.py
datastew/repository/weaviate.py
datastew/repository/weaviate_schema.py
datastew/scripts/export_json_from_weaviate.py
datastew/scripts/fill_db_example.py
datastew/scripts/mapping_db_example.py
datastew/scripts/mapping_excel_example.py
datastew/scripts/ohdsi_to_jsonl.py
datastew/scripts/ols_snomed_retrieval.py
datastew/scripts/tsne_visualization.py
datastew/visualisation.py
datastew-0.6.1.dist-info/METADATA
datastew-0.6.1.dist-info/WHEEL
datastew-0.6.1.dist-info/licenses/LICENSE
datastew-0.6.1.dist-info/RECORD
