Metadata-Version: 2.4
Name: datastew
Version: 0.6.1
Summary: Datastew is a python library for intelligent data harmonization using Large Language Model (LLM) vector embeddings.
License: Apache-2.0
License-File: LICENSE
Keywords: data-harmonization,LLM,embeddings,data-steward
Author: Tim Adams
Author-email: tim.adams@scai.fraunhofer.de
Requires-Python: >=3.10,<3.15
Classifier: Development Status :: 3 - Alpha
Classifier: Intended Audience :: Developers
Classifier: License :: OSI Approved :: Apache Software License
Classifier: Programming Language :: Python :: 3
Classifier: Programming Language :: Python :: 3.10
Classifier: Programming Language :: Python :: 3.11
Classifier: Programming Language :: Python :: 3.12
Classifier: Programming Language :: Python :: 3.13
Classifier: Programming Language :: Python :: 3.14
Requires-Dist: SQLAlchemy (>=2.0.44,<3.0.0)
Requires-Dist: aiofiles (>=25.1.0,<26.0.0)
Requires-Dist: cachetools (>=6.2.1,<7.0.0)
Requires-Dist: matplotlib (>=3.10.7,<4.0.0)
Requires-Dist: numpy (>=2.2.6,<3.0.0)
Requires-Dist: ollama (>=0.6.0,<0.7.0)
Requires-Dist: openai (>=2.7.1,<3.0.0)
Requires-Dist: openpyxl (>=3.1.5,<4.0.0)
Requires-Dist: pandas (>=2.3.3,<3.0.0)
Requires-Dist: pgvector (>=0.4.1,<0.5.0)
Requires-Dist: plotly (>=6.4.0,<7.0.0)
Requires-Dist: psycopg2-binary (>=2.9.11,<3.0.0)
Requires-Dist: pydantic (>=2.12.4,<3.0.0)
Requires-Dist: python-dateutil (>=2.9.0.post0,<3.0.0)
Requires-Dist: python-dotenv (>=1.2.1,<2.0.0)
Requires-Dist: pytz (>=2025.2,<2026.0)
Requires-Dist: requests (>=2.32.5,<3.0.0)
Requires-Dist: scikit-learn (>=1.7.2,<2.0.0)
Requires-Dist: scipy (>=1.15.3,<2.0.0)
Requires-Dist: seaborn (>=0.13.2,<0.14.0)
Requires-Dist: sentence-transformers (>=5.1.2,<6.0.0)
Requires-Dist: six (>=1.17.0,<2.0.0)
Requires-Dist: thefuzz (>=0.22.1,<0.23.0)
Requires-Dist: torch (>=2.9.0,<3.0.0)
Requires-Dist: tzdata (>=2025.2,<2026.0)
Requires-Dist: uuid (>=1.30,<2.0)
Requires-Dist: weaviate-client (>=4.17.0,<5.0.0)
Requires-Dist: wheel (>=0.45.1,<0.46.0)
Project-URL: Documentation, https://github.com/SCAI-BIO/datastew#readme
Project-URL: Homepage, https://github.com/SCAI-BIO/datastew
Project-URL: Repository, https://github.com/SCAI-BIO/datastew
Project-URL: documentation, https://github.com/SCAI-BIO/datastew#readme
Project-URL: homepage, https://github.com/SCAI-BIO/datastew
Project-URL: repository, https://github.com/SCAI-BIO/datastew
Project-URL: tracker, https://github.com/SCAI-BIO/datastew/issues
